omath/__init__.py
omath/arithmetic.py
omath/geometry.py
omath/strings.py
omath-0.1.3.dist-info/licenses/LICENSE
omath-0.1.3.dist-info/METADATA
omath-0.1.3.dist-info/WHEEL
omath-0.1.3.dist-info/top_level.txt
omath-0.1.3.dist-info/RECORD
