Metadata-Version: 2.4
Name: omath
Version: 0.1.3
Summary: Math and string utilities built from first principles - no dependencies
Author-email: Om Mishra <om.23bcs10191@ms.sst.scaler.com>
License-Expression: MIT
Project-URL: Homepage, https://github.com/OmMishra16/omath
Project-URL: Source, https://github.com/OmMishra16/omath
Project-URL: Bug Tracker, https://github.com/OmMishra16/omath/issues
Keywords: math,utilities,education,first-principles,no-dependencies
Classifier: Development Status :: 3 - Alpha
Classifier: Intended Audience :: Developers
Classifier: Intended Audience :: Education
Classifier: Programming Language :: Python :: 3
Classifier: Programming Language :: Python :: 3.8
Classifier: Programming Language :: Python :: 3.9
Classifier: Programming Language :: Python :: 3.10
Classifier: Programming Language :: Python :: 3.11
Classifier: Programming Language :: Python :: 3.12
Classifier: Programming Language :: Python :: 3.13
Classifier: Operating System :: OS Independent
Classifier: Topic :: Education
Classifier: Topic :: Software Development :: Libraries :: Python Modules
Requires-Python: >=3.8
License-File: LICENSE
Dynamic: license-file
